{
  "generatedAt": "2026-05-17T08:35:56.863Z",
  "windowDays": 3,
  "totals": {
    "units": 4,
    "unitsWithOfficialFeeds": 4,
    "autoDiscoveredUnits": 0,
    "brigades": 4,
    "brigadesWithOfficialFeeds": 4,
    "officialItems": 28,
    "mentionItems": 0,
    "significantItems": 10,
    "strikeItems": 7,
    "reorgItems": 3
  },
  "brigades": [
    {
      "id": "general-staff-ua",
      "name": "Генеральний Штаб ЗСУ",
      "aliases": [
        "Генеральний Штаб ЗСУ",
        "генеральний штаб зсу",
        "general staff ua"
      ],
      "sources": [
        {
          "platform": "x",
          "handle": "GeneralStaffUA",
          "trusted": true
        }
      ],
      "autoDiscovered": false,
      "officialItems": 18,
      "mentionItems": 0,
      "significantItems": 5,
      "strikeItems": 5,
      "reorgItems": 0,
      "hasOfficialFeed": true,
      "items": [
        {
          "id": "x-GeneralStaffUA-d79c53f2f91fdb",
          "title": "У ніч на 17 травня (з 19:00 16 травня) противник атакував 287 ударними БпЛА типу Shahed (в т.ч....",
          "summary": "У ніч на 17 травня (з 19:00 16 травня) противник атакував 287 ударними БпЛА типу Shahed (в т.ч. реактивними), Гербера, Італмас та дронами-імітаторами типу \"Пародія\" ⚡️ ЗБИТО/ПОДАВЛЕНО 279 ВОРОЖИХ БПЛА. В повітряному просторі нові групи ворожих БпЛА. Дотримуйтесь правил безпеки!",
          "url": "https://x.com/GeneralStaffUA/status/2055888692082860039",
          "publishedAt": "2026-05-17T05:50:35.000Z",
          "source": "x",
          "sourceLabel": "GeneralStaffUA",
          "origin": "official",
          "score": 5,
          "strikeScore": 3,
          "reorgScore": 0,
          "isStrike": true,
          "isReorg": false,
          "titleUk": "У ніч на 17 травня (з 19:00 16 травня) противник атакував 287 ударними БпЛА типу Shahed (в т.ч....",
          "summaryUk": "У ніч на 17 травня (з 19:00 16 травня) противник атакував 287 ударними БпЛА типу Shahed (в т.ч. реактивними), Гербера, Італмас та дронами-імітаторами типу \"Пародія\" ⚡️ ЗБИТО/ПОДАВЛЕНО 279 ВОРОЖИХ БПЛА. В повітряному просторі нові групи ворожих БпЛА. Дотримуйтесь правил безпеки!"
        },
        {
          "id": "x-GeneralStaffUA-358eec9115b552",
          "title": "У ніч на 16 травня (з 18:00 15 травня) противник атакував 294 ударними БпЛА типу Shahed (в т.ч....",
          "summary": "У ніч на 16 травня (з 18:00 15 травня) противник атакував 294 ударними БпЛА типу Shahed (в т.ч. реактивними), Гербера, Італмас та та дронами-імітаторами типу \"Пародія\" . ⚡️ ЗБИТО/ПОДАВЛЕНО 269 ВОРОЖИХ БПЛА. Атака триває, в повітряному просторі декілька ворожих БпЛА.",
          "url": "https://x.com/GeneralStaffUA/status/2055540468579004810",
          "publishedAt": "2026-05-16T06:46:52.000Z",
          "source": "x",
          "sourceLabel": "GeneralStaffUA",
          "origin": "official",
          "score": 5,
          "strikeScore": 3,
          "reorgScore": 0,
          "isStrike": true,
          "isReorg": false,
          "titleUk": "У ніч на 16 травня (з 18:00 15 травня) противник атакував 294 ударними БпЛА типу Shahed (в т.ч....",
          "summaryUk": "У ніч на 16 травня (з 18:00 15 травня) противник атакував 294 ударними БпЛА типу Shahed (в т.ч. реактивними), Гербера, Італмас та та дронами-імітаторами типу \"Пародія\" . ⚡️ ЗБИТО/ПОДАВЛЕНО 269 ВОРОЖИХ БПЛА. Атака триває, в повітряному просторі декілька ворожих БпЛА."
        },
        {
          "id": "x-GeneralStaffUA-d79d5d1ed9aa7e",
          "title": "«Богдана» - влучно й нищівно вражає ворога завдяки професіоналізму та майстернос...",
          "summary": "«Богдана» - влучно й нищівно вражає ворога завдяки професіоналізму та майстерності артилеристів 40-ї окремої артилерійської бригади імені Великого князя Вітовта.",
          "url": "https://x.com/GeneralStaffUA/status/2055929112636629133",
          "publishedAt": "2026-05-17T08:31:12.000Z",
          "source": "x",
          "sourceLabel": "GeneralStaffUA",
          "origin": "official",
          "score": 4,
          "strikeScore": 2,
          "reorgScore": 0,
          "isStrike": true,
          "isReorg": false,
          "titleUk": "«Богдана» - влучно й нищівно вражає ворога завдяки професіоналізму та майстернос...",
          "summaryUk": "«Богдана» - влучно й нищівно вражає ворога завдяки професіоналізму та майстерності артилеристів 40-ї окремої артилерійської бригади імені Великого князя Вітовта."
        },
        {
          "id": "x-GeneralStaffUA-8e9fbc22dd1fe9",
          "title": "⚡️Уражено пункти управління та інші об’єкти ворога. Уточнено результати влучань ...",
          "summary": "⚡️Уражено пункти управління та інші об’єкти ворога. Уточнено результати влучань в ніч на 15 травня по інфраструктурі Рязанського НПЗ (Рязанська обл., рф) - пошкоджено установки переробки АВТ-3, АВТ-4, АТ-6 та установку гідроочищення дизельного пального. https://www.facebook.com/share/p/1JJpnidrtH/",
          "url": "https://x.com/GeneralStaffUA/status/2055670350050934786",
          "publishedAt": "2026-05-16T15:22:58.000Z",
          "source": "x",
          "sourceLabel": "GeneralStaffUA",
          "origin": "official",
          "score": 4,
          "strikeScore": 2,
          "reorgScore": 0,
          "isStrike": true,
          "isReorg": false,
          "titleUk": "⚡️Уражено пункти управління та інші об’єкти ворога. Уточнено результати влучань ...",
          "summaryUk": "⚡️Уражено пункти управління та інші об’єкти ворога. Уточнено результати влучань в ніч на 15 травня по інфраструктурі Рязанського НПЗ (Рязанська обл., рф) - пошкоджено установки переробки АВТ-3, АВТ-4, АТ-6 та установку гідроочищення дизельного пального. https://www.facebook.com/share/p/1JJpnidrtH/"
        },
        {
          "id": "x-GeneralStaffUA-a056e028fd153b",
          "title": "RT Volodymyr Zelenskyy / Володимир Зеленський: Our long-range sanctions this week. Most of the operations are still ongoing, so the...",
          "summary": "RT Volodymyr Zelenskyy / Володимир Зеленський Our long-range sanctions this week. Most of the operations are still ongoing, so the video captures only a portion of our results. Be-200 amphibious aircraft, a Ka-27 helicopter, a cargo vessel carrying ammunition, a Pantsir-S1 surface‑to‑air missile and gun system, a Tor surface-to-air missile system, a Redut-2US communications unit, drones, and many other targets have been hit. Our long-range sanctions also struck Russian oil industry facilities and ships. Distances traversed: nearly 1,000 kilometers from the line of contact. These are our entirely justified responses to what the Russians are doing. We will continue to increase both the range and scale of these sanctions. I thank everyone working to build up our strength. I thank the warriors of the Armed Forces of Ukraine, the Security Service of Ukraine, and our intelligence agencies for their precision.",
          "url": "https://x.com/GeneralStaffUA/status/2055591836870132143",
          "publishedAt": "2026-05-16T09:00:07.000Z",
          "source": "x",
          "sourceLabel": "GeneralStaffUA",
          "origin": "official",
          "score": 3,
          "strikeScore": 1,
          "reorgScore": 0,
          "isStrike": true,
          "isReorg": false,
          "titleUk": "RT Volodymyr Zelenskyy / Володимир Зеленський: Our long-range sanctions this week. Most of the operations are still ongoing, so the...",
          "summaryUk": "RT Volodymyr Zelenskyy / Володимир Зеленський Our long-range sanctions this week. Most of the operations are still ongoing, so the video captures only a portion of our results. Be-200 amphibious aircraft, a Ka-27 helicopter, a cargo vessel carrying ammunition, a Pantsir-S1 surface‑to‑air missile and gun system, a Tor surface-to-air missile system, a Redut-2US communications unit, drones, and many other targets have been hit. Our long-range sanctions also struck Russian oil industry facilities and ships. Distances traversed: nearly 1,000 kilometers from the line of contact. These are our entirely justified responses to what the Russians are doing. We will continue to increase both the range and scale of these sanctions. I thank everyone working to build up our strength. I thank the warriors of the Armed Forces of Ukraine, the Security Service of Ukraine, and our intelligence agencies for their precision."
        },
        {
          "id": "x-GeneralStaffUA-d6f49b81b59c82",
          "title": "Загальні бойові втрати противника з 24.02.22 по 17.05.26 орієнтовно склали / The estimated total comb...",
          "summary": "Загальні бойові втрати противника з 24.02.22 по 17.05.26 орієнтовно склали / The estimated total combat losses of the enemy from 24.02.22 to 17.05.26",
          "url": "https://x.com/GeneralStaffUA/status/2055855537812619379",
          "publishedAt": "2026-05-17T03:38:50.000Z",
          "source": "x",
          "sourceLabel": "GeneralStaffUA",
          "origin": "official",
          "score": 1,
          "strikeScore": 0,
          "reorgScore": 0,
          "isStrike": false,
          "isReorg": false,
          "titleUk": "Загальні бойові втрати противника з 24.02.22 по 17.05.26 орієнтовно склали / The estimated total comb...",
          "summaryUk": "Загальні бойові втрати противника з 24.02.22 по 17.05.26 орієнтовно склали / The estimated total combat losses of the enemy from 24.02.22 to 17.05.26"
        },
        {
          "id": "x-GeneralStaffUA-6cfbc17c81abf0",
          "title": "Загальні бойові втрати противника з 24.02.22 по 16.05.26 орієнтовно склали / The estimated total comb...",
          "summary": "Загальні бойові втрати противника з 24.02.22 по 16.05.26 орієнтовно склали / The estimated total combat losses of the enemy from 24.02.22 to 16.05.26",
          "url": "https://x.com/GeneralStaffUA/status/2055497549742485726",
          "publishedAt": "2026-05-16T03:56:19.000Z",
          "source": "x",
          "sourceLabel": "GeneralStaffUA",
          "origin": "official",
          "score": 1,
          "strikeScore": 0,
          "reorgScore": 0,
          "isStrike": false,
          "isReorg": false,
          "titleUk": "Загальні бойові втрати противника з 24.02.22 по 16.05.26 орієнтовно склали / The estimated total comb...",
          "summaryUk": "Загальні бойові втрати противника з 24.02.22 по 16.05.26 орієнтовно склали / The estimated total combat losses of the enemy from 24.02.22 to 16.05.26"
        },
        {
          "id": "x-GeneralStaffUA-ebd4191b414e5b",
          "title": "Тварини на фронті — це вже невід’ємна частина буднів українських воїнів. Врятован...",
          "summary": "Тварини на фронті — це вже невід’ємна частина буднів українських воїнів. Врятованих пухнастиків не кидають напризволяще, а возять із собою під час ротацій або ж прилаштовують у добрі руки у тилу. ЗСУ — люди, які захищають кожне життя. Фото - 14 АК та 65 ОМБр",
          "url": "https://x.com/GeneralStaffUA/status/2055913658518024315",
          "publishedAt": "2026-05-17T07:29:47.000Z",
          "source": "x",
          "sourceLabel": "GeneralStaffUA",
          "origin": "official",
          "score": 0,
          "strikeScore": 0,
          "reorgScore": 0,
          "isStrike": false,
          "isReorg": false,
          "titleUk": "Тварини на фронті — це вже невід’ємна частина буднів українських воїнів. Врятован...",
          "summaryUk": "Тварини на фронті — це вже невід’ємна частина буднів українських воїнів. Врятованих пухнастиків не кидають напризволяще, а возять із собою під час ротацій або ж прилаштовують у добрі руки у тилу. ЗСУ — люди, які захищають кожне життя. Фото - 14 АК та 65 ОМБр"
        }
      ]
    },
    {
      "id": "13-khartia",
      "name": "13 Бригада НГУ «Хартія»",
      "aliases": [
        "13 Бригада НГУ «Хартія»",
        "хартія",
        "13 бригада нгу",
        "khartia brigade",
        "13th operational brigade"
      ],
      "sources": [
        {
          "platform": "x",
          "handle": "khartiiabrygada",
          "trusted": true
        }
      ],
      "autoDiscovered": false,
      "officialItems": 6,
      "mentionItems": 0,
      "significantItems": 4,
      "strikeItems": 2,
      "reorgItems": 2,
      "hasOfficialFeed": true,
      "items": [
        {
          "id": "x-khartiiabrygada-5ec2499b372222",
          "title": "Повітряні бої з ворожими безпілотниками – робота хартійських дронарів! Вони ціло...",
          "summary": "Повітряні бої з ворожими безпілотниками – робота хартійських дронарів! Вони цілодобово збивають БпЛА загарбника, що загрожують і нашим військовим, і цивільним. Долучайтесь до «Хартії» – захищайте українське небо! Телефонуйте нашим рекрутерам на короткий номер 3333.",
          "url": "https://x.com/khartiiabrygada/status/2054931838582309255",
          "publishedAt": "2026-05-14T14:28:23.000Z",
          "source": "x",
          "sourceLabel": "khartiiabrygada",
          "origin": "official",
          "score": 4,
          "strikeScore": 2,
          "reorgScore": 0,
          "isStrike": true,
          "isReorg": false,
          "titleUk": "Повітряні бої з ворожими безпілотниками – робота хартійських дронарів! Вони ціло...",
          "summaryUk": "Повітряні бої з ворожими безпілотниками – робота хартійських дронарів! Вони цілодобово збивають БпЛА загарбника, що загрожують і нашим військовим, і цивільним. Долучайтесь до «Хартії» – захищайте українське небо! Телефонуйте нашим рекрутерам на короткий номер 3333."
        },
        {
          "id": "x-khartiiabrygada-fc3ce8c82708b4",
          "title": "Герой України – Андрій «Гром» Іщенко – командир 4-го батальйону 23-го полку РУГ 2-го ...",
          "summary": "Герой України – Андрій «Гром» Іщенко – командир 4-го батальйону 23-го полку РУГ 2-го корпусу НГУ «Хартія». Друг «Гром» повернувся в стрій після важкого поранення, якого зазнав під час зачистки на Куп’янщині, де він особисто вів у бій штурмові групи.",
          "url": "https://x.com/khartiiabrygada/status/2055634749121564997",
          "publishedAt": "2026-05-16T13:01:30.000Z",
          "source": "x",
          "sourceLabel": "khartiiabrygada",
          "origin": "official",
          "score": 3,
          "strikeScore": 0,
          "reorgScore": 1,
          "isStrike": false,
          "isReorg": true,
          "titleUk": "Герой України – Андрій «Гром» Іщенко – командир 4-го батальйону 23-го полку РУГ 2-го ...",
          "summaryUk": "Герой України – Андрій «Гром» Іщенко – командир 4-го батальйону 23-го полку РУГ 2-го корпусу НГУ «Хартія». Друг «Гром» повернувся в стрій після важкого поранення, якого зазнав під час зачистки на Куп’янщині, де він особисто вів у бій штурмові групи."
        },
        {
          "id": "x-khartiiabrygada-487eb528bc77f2",
          "title": "Очі ворога в небі – російські крила-розвідники – важлива ціль для хартійських пов...",
          "summary": "Очі ворога в небі – російські крила-розвідники – важлива ціль для хартійських повітряних перехоплювачів. Удень і вночі дронарі полюють за «Орланами», «Форпостами», ZALA та Supercam, аби вбезпечити наші позиції та техніку. Тримаємо українське небо!",
          "url": "https://x.com/khartiiabrygada/status/2055328802956316830",
          "publishedAt": "2026-05-15T16:45:47.000Z",
          "source": "x",
          "sourceLabel": "khartiiabrygada",
          "origin": "official",
          "score": 3,
          "strikeScore": 1,
          "reorgScore": 0,
          "isStrike": true,
          "isReorg": false,
          "titleUk": "Очі ворога в небі – російські крила-розвідники – важлива ціль для хартійських пов...",
          "summaryUk": "Очі ворога в небі – російські крила-розвідники – важлива ціль для хартійських повітряних перехоплювачів. Удень і вночі дронарі полюють за «Орланами», «Форпостами», ZALA та Supercam, аби вбезпечити наші позиції та техніку. Тримаємо українське небо!"
        },
        {
          "id": "x-khartiiabrygada-8a1ad93aff7a7e",
          "title": "Гаряча вакансія до корпусу «Хартія» – шукаємо фахівця взаємодії з органами влади!...",
          "summary": "Гаряча вакансія до корпусу «Хартія» – шукаємо фахівця взаємодії з органами влади! Підрозділи нашого корпусу постійно комунікують з місцевими громадами – зокрема, щодо матеріальної допомоги та субвенцій. Дізнавайтеся деталі за посиланням: http://work.ua/en/jobs/8008533/",
          "url": "https://x.com/khartiiabrygada/status/2055240699407143394",
          "publishedAt": "2026-05-15T10:55:41.000Z",
          "source": "x",
          "sourceLabel": "khartiiabrygada",
          "origin": "official",
          "score": 2,
          "strikeScore": 0,
          "reorgScore": 1,
          "isStrike": false,
          "isReorg": true,
          "titleUk": "Гаряча вакансія до корпусу «Хартія» – шукаємо фахівця взаємодії з органами влади!...",
          "summaryUk": "Гаряча вакансія до корпусу «Хартія» – шукаємо фахівця взаємодії з органами влади! Підрозділи нашого корпусу постійно комунікують з місцевими громадами – зокрема, щодо матеріальної допомоги та субвенцій. Дізнавайтеся деталі за посиланням: http://work.ua/en/jobs/8008533/"
        },
        {
          "id": "x-khartiiabrygada-519bdca5a58969",
          "title": "Усі наші зусилля направлені на те, щоб допомогти піхотинцю. Саме від дій піхоти за...",
          "summary": "Усі наші зусилля направлені на те, щоб допомогти піхотинцю. Саме від дій піхоти залежить, чи відстояли ми нашу землю. І саме піхота найбільше ризикує життям, адже ворог не шкодує власних сил і засобів навіть заради клаптика української території.",
          "url": "https://x.com/khartiiabrygada/status/2055299579675890045",
          "publishedAt": "2026-05-15T14:49:40.000Z",
          "source": "x",
          "sourceLabel": "khartiiabrygada",
          "origin": "official",
          "score": 1,
          "strikeScore": 0,
          "reorgScore": 0,
          "isStrike": false,
          "isReorg": false,
          "titleUk": "Усі наші зусилля направлені на те, щоб допомогти піхотинцю. Саме від дій піхоти за...",
          "summaryUk": "Усі наші зусилля направлені на те, щоб допомогти піхотинцю. Саме від дій піхоти залежить, чи відстояли ми нашу землю. І саме піхота найбільше ризикує життям, адже ворог не шкодує власних сил і засобів навіть заради клаптика української території."
        },
        {
          "id": "x-khartiiabrygada-146b9d0bfc1e4c",
          "title": "Вітаємо з Днем народження Святослава Вакарчука – щирого друга «Хартії», який уже ...",
          "summary": "Вітаємо з Днем народження Святослава Вакарчука – щирого друга «Хартії», який уже давно підтримує наш підрозділ. Многая літа!",
          "url": "https://x.com/khartiiabrygada/status/2054953208175292731",
          "publishedAt": "2026-05-14T15:53:18.000Z",
          "source": "x",
          "sourceLabel": "khartiiabrygada",
          "origin": "official",
          "score": 0,
          "strikeScore": 0,
          "reorgScore": 0,
          "isStrike": false,
          "isReorg": false,
          "titleUk": "Вітаємо з Днем народження Святослава Вакарчука – щирого друга «Хартії», який уже ...",
          "summaryUk": "Вітаємо з Днем народження Святослава Вакарчука – щирого друга «Хартії», який уже давно підтримує наш підрозділ. Многая літа!"
        }
      ]
    },
    {
      "id": "3-iron",
      "name": "3 ОВМБр «Залізна»",
      "aliases": [
        "3 ОВМБр «Залізна»",
        "3 овмбр",
        "залізна бригада",
        "3 iron brigade",
        "3 важка механізована"
      ],
      "sources": [
        {
          "platform": "x",
          "handle": "3ironbrigade",
          "trusted": true
        }
      ],
      "autoDiscovered": false,
      "officialItems": 3,
      "mentionItems": 0,
      "significantItems": 1,
      "strikeItems": 0,
      "reorgItems": 1,
      "hasOfficialFeed": true,
      "items": [
        {
          "id": "x-3ironbrigade-773a79c56d0518",
          "title": "«Вступаючи до лав…, я присягаю…», — линуть до неба крізь гілля прифронтового гаю с...",
          "summary": "«Вступаючи до лав…, я присягаю…», — линуть до неба крізь гілля прифронтового гаю слова клятви. Колишні рекрути, пройшовши перший вишкіл — базову загальновійськову підготовку, приєднуються до лицарського колективу Залізної бригади. Новобранці, загартовані напруженими навчаннями в умовах, максимально наближених до бойових, озброєні новими знаннями та навичками, стали повноцінними солдатами. На підтвердження зміни статусу інструктори та офіцери-психологи та вручили їм нарукавний знак з’єднання, що вже став символом незламності та відваги «залізних лицарів». Нова традиція з урочистою церемонію врученням символіки з’єднання, нещодавно започаткована за ініціативи командування з’єднання, вже отримала схвальні відгуки перших випускників «польової академії залізного лицарства». За їхніми словами, вона неабияк надихає та мотивує бійців. З новим етапом життя та вступом до великого братерства, від імені командування бійців привітав заступник командира бригади з психологічної підтримки персоналу. Гомін, сміх, вітання, дружні обійми та групове фото на згадку... Попереду нових «залізних лицарів» чекає головний екзамен — виконання бойових завдань на передовій.",
          "url": "https://x.com/3ironbrigade/status/2055173560079876433",
          "publishedAt": "2026-05-15T06:28:54.000Z",
          "source": "x",
          "sourceLabel": "3ironbrigade",
          "origin": "official",
          "score": 2,
          "strikeScore": 0,
          "reorgScore": 1,
          "isStrike": false,
          "isReorg": true,
          "titleUk": "«Вступаючи до лав…, я присягаю…», — линуть до неба крізь гілля прифронтового гаю с...",
          "summaryUk": "«Вступаючи до лав…, я присягаю…», — линуть до неба крізь гілля прифронтового гаю слова клятви. Колишні рекрути, пройшовши перший вишкіл — базову загальновійськову підготовку, приєднуються до лицарського колективу Залізної бригади. Новобранці, загартовані напруженими навчаннями в умовах, максимально наближених до бойових, озброєні новими знаннями та навичками, стали повноцінними солдатами. На підтвердження зміни статусу інструктори та офіцери-психологи та вручили їм нарукавний знак з’єднання, що вже став символом незламності та відваги «залізних лицарів». Нова традиція з урочистою церемонію врученням символіки з’єднання, нещодавно започаткована за ініціативи командування з’єднання, вже отримала схвальні відгуки перших випускників «польової академії залізного лицарства». За їхніми словами, вона неабияк надихає та мотивує бійців. З новим етапом життя та вступом до великого братерства, від імені командування бійців привітав заступник командира бригади з психологічної підтримки персоналу. Гомін, сміх, вітання, дружні обійми та групове фото на згадку... Попереду нових «залізних лицарів» чекає головний екзамен — виконання бойових завдань на передовій."
        },
        {
          "id": "x-3ironbrigade-e0552f0abf3645",
          "title": "СЗЧ — не вирок! Ми допоможемо тобі. Приєднуйся до нашого лицарського колективу! Об...",
          "summary": "СЗЧ — не вирок! Ми допоможемо тобі. Приєднуйся до нашого лицарського колективу! Обирай посаду у Залізній бригаді, де толкові командири цінують людей, їхній досвід, знання та навички. Потурбуємося про зняття відповідальності за СЗЧ. Гарантуємо службу за фахом, достойну платню, дружній колектив та людяне ставлення. Заповни анкету та поверни собі впевненість у власних силах. ---------------------------- Анкета за посиланням — https://forms.gle/B7kQ6upH1yxJHZfM8",
          "url": "https://x.com/3ironbrigade/status/2055899443711316399",
          "publishedAt": "2026-05-17T06:33:18.000Z",
          "source": "x",
          "sourceLabel": "3ironbrigade",
          "origin": "official",
          "score": 0,
          "strikeScore": 0,
          "reorgScore": 0,
          "isStrike": false,
          "isReorg": false,
          "titleUk": "СЗЧ — не вирок! Ми допоможемо тобі. Приєднуйся до нашого лицарського колективу! Об...",
          "summaryUk": "СЗЧ — не вирок! Ми допоможемо тобі. Приєднуйся до нашого лицарського колективу! Обирай посаду у Залізній бригаді, де толкові командири цінують людей, їхній досвід, знання та навички. Потурбуємося про зняття відповідальності за СЗЧ. Гарантуємо службу за фахом, достойну платню, дружній колектив та людяне ставлення. Заповни анкету та поверни собі впевненість у власних силах. ---------------------------- Анкета за посиланням — https://forms.gle/B7kQ6upH1yxJHZfM8"
        },
        {
          "id": "x-3ironbrigade-10c1e53451a635",
          "title": "Різні за віком, характерами, освітою та професіями. Вони не мріяли про подвиги та з...",
          "summary": "Різні за віком, характерами, освітою та професіями. Вони не мріяли про подвиги та звитягу. Але у лихий для країни час доля обрала їм один, спільний шлях — шлях воїна. Коли прийшов час взяти до рук зброю, вони не втікали, не ховалися, а з спокійною зосередженістю, з якою звикли працювати у мирний час, вирушили на захист України від споконвічного ворога. Щирі, мудрі, та цілеспрямовані, вони стали бійцями Залізної бригади та опанували нову для себе науку — бути солдатом-захисником. За їхніми спинами залишилися матері, дружини, діти, рідні та друзі, заради яких вони готові йти до кінця.",
          "url": "https://x.com/3ironbrigade/status/2055543951273136332",
          "publishedAt": "2026-05-16T07:00:42.000Z",
          "source": "x",
          "sourceLabel": "3ironbrigade",
          "origin": "official",
          "score": 0,
          "strikeScore": 0,
          "reorgScore": 0,
          "isStrike": false,
          "isReorg": false,
          "titleUk": "Різні за віком, характерами, освітою та професіями. Вони не мріяли про подвиги та з...",
          "summaryUk": "Різні за віком, характерами, освітою та професіями. Вони не мріяли про подвиги та звитягу. Але у лихий для країни час доля обрала їм один, спільний шлях — шлях воїна. Коли прийшов час взяти до рук зброю, вони не втікали, не ховалися, а з спокійною зосередженістю, з якою звикли працювати у мирний час, вирушили на захист України від споконвічного ворога. Щирі, мудрі, та цілеспрямовані, вони стали бійцями Залізної бригади та опанували нову для себе науку — бути солдатом-захисником. За їхніми спинами залишилися матері, дружини, діти, рідні та друзі, заради яких вони готові йти до кінця."
        }
      ]
    },
    {
      "id": "28-ombr",
      "name": "28 ОМБр імені Лицарів Зимового Походу",
      "aliases": [
        "28 ОМБр імені Лицарів Зимового Походу",
        "28 омбр",
        "28th mechanized brigade"
      ],
      "sources": [
        {
          "platform": "x",
          "handle": "28ombr",
          "trusted": true
        }
      ],
      "autoDiscovered": false,
      "officialItems": 1,
      "mentionItems": 0,
      "significantItems": 0,
      "strikeItems": 0,
      "reorgItems": 0,
      "hasOfficialFeed": true,
      "items": [
        {
          "id": "x-28ombr-66d6069a89b967",
          "title": "A new group of foreign volunteers has joined the 28th Brigade’s UAV Battalion “Spalakh” after completing training and combat preparation. Different...",
          "summary": "A new group of foreign volunteers has joined the 28th Brigade’s UAV Battalion “Spalakh” after completing training and combat preparation. Different languages. Different countries. One goal — defeat the evil threatening far more than Ukraine. Join us. 🫡 #Ukraine",
          "url": "https://x.com/28ombr/status/2054861517707706860",
          "publishedAt": "2026-05-14T09:48:57.000Z",
          "source": "x",
          "sourceLabel": "28ombr",
          "origin": "official",
          "score": 0,
          "strikeScore": 0,
          "reorgScore": 0,
          "isStrike": false,
          "isReorg": false,
          "titleUk": "До складу батальйону БПЛА «Спалах» 28-ї бригади після проходження навчально-бойової підготовки приєдналася нова група іноземних добровольців. Різні...",
          "summaryUk": "До складу батальйону БПЛА «Спалах» 28-ї бригади після проходження навчально-бойової підготовки приєдналася нова група іноземних добровольців. Різні мови. Різні країни. Мета одна — перемогти зло, яке загрожує набагато більше, ніж Україні. приєднуйтесь до нас 🫡 #Україна"
        }
      ]
    }
  ]
}
