{
  "generatedAt": "2026-05-31T17:20:58.823Z",
  "channel": "pechalbeda200",
  "sourceUrl": "https://t.me/s/pechalbeda200",
  "methodology": {
    "windowDays": 30,
    "note": "Counts are based on public posts in Telegram web channel view. totalBySerial uses the numeric index at the start of entry text; fallback totalApproxByMaxPostId uses maximum observed channel post ID. This job should run often because the channel updates many times per day."
  },
  "counters": {
    "today": 46,
    "last7Days": 611,
    "last30Days": 648,
    "totalBySerial": 210045,
    "totalApproxByMaxPostId": 367010
  },
  "days": [
    {
      "day": "2026-05-24",
      "count": 75
    },
    {
      "day": "2026-05-25",
      "count": 91
    },
    {
      "day": "2026-05-26",
      "count": 102
    },
    {
      "day": "2026-05-27",
      "count": 58
    },
    {
      "day": "2026-05-28",
      "count": 119
    },
    {
      "day": "2026-05-29",
      "count": 110
    },
    {
      "day": "2026-05-30",
      "count": 47
    },
    {
      "day": "2026-05-31",
      "count": 46
    }
  ],
  "latestProofs": [
    {
      "id": 367010,
      "datetime": "2026-05-31T17:18:59+00:00",
      "url": "https://t.me/pechalbeda200/367010",
      "dayKyiv": "2026-05-31",
      "serial": 210045
    },
    {
      "id": 367006,
      "datetime": "2026-05-31T17:17:34+00:00",
      "url": "https://t.me/pechalbeda200/367006",
      "dayKyiv": "2026-05-31",
      "serial": 210043
    },
    {
      "id": 367004,
      "datetime": "2026-05-31T17:13:37+00:00",
      "url": "https://t.me/pechalbeda200/367004",
      "dayKyiv": "2026-05-31",
      "serial": 210041
    },
    {
      "id": 367002,
      "datetime": "2026-05-31T17:12:05+00:00",
      "url": "https://t.me/pechalbeda200/367002",
      "dayKyiv": "2026-05-31",
      "serial": 210039
    },
    {
      "id": 367000,
      "datetime": "2026-05-31T17:08:05+00:00",
      "url": "https://t.me/pechalbeda200/367000",
      "dayKyiv": "2026-05-31",
      "serial": 210037
    },
    {
      "id": 366996,
      "datetime": "2026-05-31T16:57:59+00:00",
      "url": "https://t.me/pechalbeda200/366996",
      "dayKyiv": "2026-05-31",
      "serial": 210035
    },
    {
      "id": 366993,
      "datetime": "2026-05-31T16:55:50+00:00",
      "url": "https://t.me/pechalbeda200/366993",
      "dayKyiv": "2026-05-31",
      "serial": 210033
    },
    {
      "id": 366989,
      "datetime": "2026-05-31T16:49:58+00:00",
      "url": "https://t.me/pechalbeda200/366989",
      "dayKyiv": "2026-05-31",
      "serial": 210030
    },
    {
      "id": 366986,
      "datetime": "2026-05-31T16:47:17+00:00",
      "url": "https://t.me/pechalbeda200/366986",
      "dayKyiv": "2026-05-31",
      "serial": 210028
    },
    {
      "id": 366982,
      "datetime": "2026-05-31T16:40:42+00:00",
      "url": "https://t.me/pechalbeda200/366982",
      "dayKyiv": "2026-05-31",
      "serial": 210026
    },
    {
      "id": 366979,
      "datetime": "2026-05-31T16:38:12+00:00",
      "url": "https://t.me/pechalbeda200/366979",
      "dayKyiv": "2026-05-31",
      "serial": 210024
    },
    {
      "id": 366977,
      "datetime": "2026-05-31T16:36:33+00:00",
      "url": "https://t.me/pechalbeda200/366977",
      "dayKyiv": "2026-05-31",
      "serial": 210022
    },
    {
      "id": 366975,
      "datetime": "2026-05-31T16:32:18+00:00",
      "url": "https://t.me/pechalbeda200/366975",
      "dayKyiv": "2026-05-31",
      "serial": 210020
    },
    {
      "id": 366973,
      "datetime": "2026-05-31T16:29:10+00:00",
      "url": "https://t.me/pechalbeda200/366973",
      "dayKyiv": "2026-05-31",
      "serial": 210018
    },
    {
      "id": 366967,
      "datetime": "2026-05-31T15:39:30+00:00",
      "url": "https://t.me/pechalbeda200/366967",
      "dayKyiv": "2026-05-31",
      "serial": 210016
    },
    {
      "id": 366962,
      "datetime": "2026-05-31T15:34:00+00:00",
      "url": "https://t.me/pechalbeda200/366962",
      "dayKyiv": "2026-05-31",
      "serial": 210014
    },
    {
      "id": 366956,
      "datetime": "2026-05-31T15:18:14+00:00",
      "url": "https://t.me/pechalbeda200/366956",
      "dayKyiv": "2026-05-31",
      "serial": 210012
    },
    {
      "id": 366951,
      "datetime": "2026-05-31T14:50:06+00:00",
      "url": "https://t.me/pechalbeda200/366951",
      "dayKyiv": "2026-05-31",
      "serial": 210010
    },
    {
      "id": 366947,
      "datetime": "2026-05-31T14:13:00+00:00",
      "url": "https://t.me/pechalbeda200/366947",
      "dayKyiv": "2026-05-31",
      "serial": 210008
    },
    {
      "id": 366944,
      "datetime": "2026-05-31T13:41:47+00:00",
      "url": "https://t.me/pechalbeda200/366944",
      "dayKyiv": "2026-05-31",
      "serial": 210006
    }
  ]
}
