{
  "generatedAt": "2026-06-02T16:53:47.022Z",
  "channel": "pechalbeda200",
  "sourceUrl": "https://t.me/s/pechalbeda200",
  "methodology": {
    "windowDays": 30,
    "note": "Counts are based on public posts in Telegram web channel view. totalBySerial uses the numeric index at the start of entry text; fallback totalApproxByMaxPostId uses maximum observed channel post ID. This job should run often because the channel updates many times per day."
  },
  "counters": {
    "today": 81,
    "last7Days": 573,
    "last30Days": 667,
    "totalBySerial": 210368,
    "totalApproxByMaxPostId": 367559
  },
  "days": [
    {
      "day": "2026-05-25",
      "count": 26
    },
    {
      "day": "2026-05-26",
      "count": 102
    },
    {
      "day": "2026-05-27",
      "count": 58
    },
    {
      "day": "2026-05-28",
      "count": 121
    },
    {
      "day": "2026-05-29",
      "count": 111
    },
    {
      "day": "2026-05-30",
      "count": 47
    },
    {
      "day": "2026-05-31",
      "count": 63
    },
    {
      "day": "2026-06-01",
      "count": 58
    },
    {
      "day": "2026-06-02",
      "count": 81
    }
  ],
  "latestProofs": [
    {
      "id": 367559,
      "datetime": "2026-06-02T16:26:03+00:00",
      "url": "https://t.me/pechalbeda200/367559",
      "dayKyiv": "2026-06-02",
      "serial": 210368
    },
    {
      "id": 367557,
      "datetime": "2026-06-02T16:23:58+00:00",
      "url": "https://t.me/pechalbeda200/367557",
      "dayKyiv": "2026-06-02",
      "serial": 210366
    },
    {
      "id": 367555,
      "datetime": "2026-06-02T16:22:40+00:00",
      "url": "https://t.me/pechalbeda200/367555",
      "dayKyiv": "2026-06-02",
      "serial": 210364
    },
    {
      "id": 367553,
      "datetime": "2026-06-02T16:21:48+00:00",
      "url": "https://t.me/pechalbeda200/367553",
      "dayKyiv": "2026-06-02",
      "serial": 210362
    },
    {
      "id": 367551,
      "datetime": "2026-06-02T14:55:54+00:00",
      "url": "https://t.me/pechalbeda200/367551",
      "dayKyiv": "2026-06-02",
      "serial": 210360
    },
    {
      "id": 367542,
      "datetime": "2026-06-02T14:48:29+00:00",
      "url": "https://t.me/pechalbeda200/367542",
      "dayKyiv": "2026-06-02",
      "serial": 210358
    },
    {
      "id": 367538,
      "datetime": "2026-06-02T14:11:49+00:00",
      "url": "https://t.me/pechalbeda200/367538",
      "dayKyiv": "2026-06-02",
      "serial": 210356
    },
    {
      "id": 367534,
      "datetime": "2026-06-02T14:02:32+00:00",
      "url": "https://t.me/pechalbeda200/367534",
      "dayKyiv": "2026-06-02",
      "serial": 210354
    },
    {
      "id": 367529,
      "datetime": "2026-06-02T13:40:43+00:00",
      "url": "https://t.me/pechalbeda200/367529",
      "dayKyiv": "2026-06-02",
      "serial": 210352
    },
    {
      "id": 367526,
      "datetime": "2026-06-02T11:37:31+00:00",
      "url": "https://t.me/pechalbeda200/367526",
      "dayKyiv": "2026-06-02",
      "serial": 210350
    },
    {
      "id": 367524,
      "datetime": "2026-06-02T11:33:50+00:00",
      "url": "https://t.me/pechalbeda200/367524",
      "dayKyiv": "2026-06-02",
      "serial": 210348
    },
    {
      "id": 367522,
      "datetime": "2026-06-02T11:31:14+00:00",
      "url": "https://t.me/pechalbeda200/367522",
      "dayKyiv": "2026-06-02",
      "serial": 210346
    },
    {
      "id": 367520,
      "datetime": "2026-06-02T11:28:52+00:00",
      "url": "https://t.me/pechalbeda200/367520",
      "dayKyiv": "2026-06-02",
      "serial": 210344
    },
    {
      "id": 367518,
      "datetime": "2026-06-02T11:25:46+00:00",
      "url": "https://t.me/pechalbeda200/367518",
      "dayKyiv": "2026-06-02",
      "serial": 210342
    },
    {
      "id": 367516,
      "datetime": "2026-06-02T11:23:26+00:00",
      "url": "https://t.me/pechalbeda200/367516",
      "dayKyiv": "2026-06-02",
      "serial": 210340
    },
    {
      "id": 367514,
      "datetime": "2026-06-02T11:20:44+00:00",
      "url": "https://t.me/pechalbeda200/367514",
      "dayKyiv": "2026-06-02",
      "serial": 210338
    },
    {
      "id": 367512,
      "datetime": "2026-06-02T11:08:46+00:00",
      "url": "https://t.me/pechalbeda200/367512",
      "dayKyiv": "2026-06-02",
      "serial": 210336
    },
    {
      "id": 367510,
      "datetime": "2026-06-02T11:03:00+00:00",
      "url": "https://t.me/pechalbeda200/367510",
      "dayKyiv": "2026-06-02",
      "serial": 210334
    },
    {
      "id": 367508,
      "datetime": "2026-06-02T11:00:35+00:00",
      "url": "https://t.me/pechalbeda200/367508",
      "dayKyiv": "2026-06-02",
      "serial": 210332
    },
    {
      "id": 367505,
      "datetime": "2026-06-02T09:37:01+00:00",
      "url": "https://t.me/pechalbeda200/367505",
      "dayKyiv": "2026-06-02",
      "serial": 210330
    }
  ]
}
