{
  "generatedAt": "2026-06-20T21:39:08.013Z",
  "channel": "pechalbeda200",
  "sourceUrl": "https://t.me/s/pechalbeda200",
  "methodology": {
    "windowDays": 30,
    "note": "Counts are based on public posts in Telegram web channel view. totalBySerial uses the numeric index at the start of entry text; fallback totalApproxByMaxPostId uses maximum observed channel post ID. This job should run often because the channel updates many times per day."
  },
  "counters": {
    "today": 0,
    "last7Days": 545,
    "last30Days": 635,
    "totalBySerial": 213560,
    "totalApproxByMaxPostId": 373367
  },
  "days": [
    {
      "day": "2026-06-12",
      "count": 11
    },
    {
      "day": "2026-06-13",
      "count": 71
    },
    {
      "day": "2026-06-14",
      "count": 73
    },
    {
      "day": "2026-06-15",
      "count": 120
    },
    {
      "day": "2026-06-16",
      "count": 72
    },
    {
      "day": "2026-06-17",
      "count": 81
    },
    {
      "day": "2026-06-18",
      "count": 46
    },
    {
      "day": "2026-06-19",
      "count": 84
    },
    {
      "day": "2026-06-20",
      "count": 77
    }
  ],
  "latestProofs": [
    {
      "id": 373367,
      "datetime": "2026-06-20T19:55:23+00:00",
      "url": "https://t.me/pechalbeda200/373367",
      "dayKyiv": "2026-06-20",
      "serial": 213560
    },
    {
      "id": 373363,
      "datetime": "2026-06-20T19:53:09+00:00",
      "url": "https://t.me/pechalbeda200/373363",
      "dayKyiv": "2026-06-20",
      "serial": 213558
    },
    {
      "id": 373358,
      "datetime": "2026-06-20T19:51:27+00:00",
      "url": "https://t.me/pechalbeda200/373358",
      "dayKyiv": "2026-06-20",
      "serial": 213556
    },
    {
      "id": 373353,
      "datetime": "2026-06-20T19:49:38+00:00",
      "url": "https://t.me/pechalbeda200/373353",
      "dayKyiv": "2026-06-20",
      "serial": 213554
    },
    {
      "id": 373347,
      "datetime": "2026-06-20T19:48:22+00:00",
      "url": "https://t.me/pechalbeda200/373347",
      "dayKyiv": "2026-06-20",
      "serial": 213552
    },
    {
      "id": 373344,
      "datetime": "2026-06-20T19:46:58+00:00",
      "url": "https://t.me/pechalbeda200/373344",
      "dayKyiv": "2026-06-20",
      "serial": 213550
    },
    {
      "id": 373337,
      "datetime": "2026-06-20T19:45:54+00:00",
      "url": "https://t.me/pechalbeda200/373337",
      "dayKyiv": "2026-06-20",
      "serial": 213548
    },
    {
      "id": 373333,
      "datetime": "2026-06-20T19:43:01+00:00",
      "url": "https://t.me/pechalbeda200/373333",
      "dayKyiv": "2026-06-20",
      "serial": 213546
    },
    {
      "id": 373326,
      "datetime": "2026-06-20T19:40:55+00:00",
      "url": "https://t.me/pechalbeda200/373326",
      "dayKyiv": "2026-06-20",
      "serial": 213543
    },
    {
      "id": 373323,
      "datetime": "2026-06-20T19:39:36+00:00",
      "url": "https://t.me/pechalbeda200/373323",
      "dayKyiv": "2026-06-20",
      "serial": 213541
    },
    {
      "id": 373319,
      "datetime": "2026-06-20T19:38:21+00:00",
      "url": "https://t.me/pechalbeda200/373319",
      "dayKyiv": "2026-06-20",
      "serial": 213539
    },
    {
      "id": 373316,
      "datetime": "2026-06-20T19:36:41+00:00",
      "url": "https://t.me/pechalbeda200/373316",
      "dayKyiv": "2026-06-20",
      "serial": 213537
    },
    {
      "id": 373312,
      "datetime": "2026-06-20T19:34:09+00:00",
      "url": "https://t.me/pechalbeda200/373312",
      "dayKyiv": "2026-06-20",
      "serial": 213535
    },
    {
      "id": 373308,
      "datetime": "2026-06-20T19:27:49+00:00",
      "url": "https://t.me/pechalbeda200/373308",
      "dayKyiv": "2026-06-20",
      "serial": 213532
    },
    {
      "id": 373304,
      "datetime": "2026-06-20T19:20:15+00:00",
      "url": "https://t.me/pechalbeda200/373304",
      "dayKyiv": "2026-06-20",
      "serial": 213530
    },
    {
      "id": 373302,
      "datetime": "2026-06-20T19:18:36+00:00",
      "url": "https://t.me/pechalbeda200/373302",
      "dayKyiv": "2026-06-20",
      "serial": 213528
    },
    {
      "id": 373298,
      "datetime": "2026-06-20T19:16:51+00:00",
      "url": "https://t.me/pechalbeda200/373298",
      "dayKyiv": "2026-06-20",
      "serial": 213526
    },
    {
      "id": 373295,
      "datetime": "2026-06-20T19:05:02+00:00",
      "url": "https://t.me/pechalbeda200/373295",
      "dayKyiv": "2026-06-20",
      "serial": 213524
    },
    {
      "id": 373292,
      "datetime": "2026-06-20T19:02:49+00:00",
      "url": "https://t.me/pechalbeda200/373292",
      "dayKyiv": "2026-06-20",
      "serial": 213522
    },
    {
      "id": 373288,
      "datetime": "2026-06-20T18:53:22+00:00",
      "url": "https://t.me/pechalbeda200/373288",
      "dayKyiv": "2026-06-20",
      "serial": 213519
    }
  ]
}
