{
  "generatedAt": "2026-07-06T15:54:04.591Z",
  "channel": "pechalbeda200",
  "sourceUrl": "https://t.me/s/pechalbeda200",
  "methodology": {
    "windowDays": 30,
    "note": "Counts are based on public posts in Telegram web channel view. totalBySerial uses the numeric index at the start of entry text; fallback totalApproxByMaxPostId uses maximum observed channel post ID. This job should run often because the channel updates many times per day."
  },
  "counters": {
    "today": 34,
    "last7Days": 437,
    "last30Days": 620,
    "totalBySerial": 215891,
    "totalApproxByMaxPostId": 377701
  },
  "days": [
    {
      "day": "2026-06-27",
      "count": 69
    },
    {
      "day": "2026-06-28",
      "count": 80
    },
    {
      "day": "2026-06-29",
      "count": 50
    },
    {
      "day": "2026-06-30",
      "count": 48
    },
    {
      "day": "2026-07-01",
      "count": 72
    },
    {
      "day": "2026-07-02",
      "count": 103
    },
    {
      "day": "2026-07-03",
      "count": 51
    },
    {
      "day": "2026-07-04",
      "count": 71
    },
    {
      "day": "2026-07-05",
      "count": 42
    },
    {
      "day": "2026-07-06",
      "count": 34
    }
  ],
  "latestProofs": [
    {
      "id": 377701,
      "datetime": "2026-07-06T15:51:14+00:00",
      "url": "https://t.me/pechalbeda200/377701",
      "dayKyiv": "2026-07-06",
      "serial": 215891
    },
    {
      "id": 377697,
      "datetime": "2026-07-06T15:47:51+00:00",
      "url": "https://t.me/pechalbeda200/377697",
      "dayKyiv": "2026-07-06",
      "serial": 215889
    },
    {
      "id": 377695,
      "datetime": "2026-07-06T15:43:47+00:00",
      "url": "https://t.me/pechalbeda200/377695",
      "dayKyiv": "2026-07-06",
      "serial": 215887
    },
    {
      "id": 377693,
      "datetime": "2026-07-06T15:42:15+00:00",
      "url": "https://t.me/pechalbeda200/377693",
      "dayKyiv": "2026-07-06",
      "serial": 215885
    },
    {
      "id": 377691,
      "datetime": "2026-07-06T15:40:40+00:00",
      "url": "https://t.me/pechalbeda200/377691",
      "dayKyiv": "2026-07-06",
      "serial": 215883
    },
    {
      "id": 377683,
      "datetime": "2026-07-06T15:02:40+00:00",
      "url": "https://t.me/pechalbeda200/377683",
      "dayKyiv": "2026-07-06",
      "serial": 215881
    },
    {
      "id": 377675,
      "datetime": "2026-07-06T14:35:08+00:00",
      "url": "https://t.me/pechalbeda200/377675",
      "dayKyiv": "2026-07-06",
      "serial": 215879
    },
    {
      "id": 377672,
      "datetime": "2026-07-06T12:23:23+00:00",
      "url": "https://t.me/pechalbeda200/377672",
      "dayKyiv": "2026-07-06",
      "serial": 215877
    },
    {
      "id": 377670,
      "datetime": "2026-07-06T12:22:29+00:00",
      "url": "https://t.me/pechalbeda200/377670",
      "dayKyiv": "2026-07-06",
      "serial": 215875
    },
    {
      "id": 377668,
      "datetime": "2026-07-06T12:20:22+00:00",
      "url": "https://t.me/pechalbeda200/377668",
      "dayKyiv": "2026-07-06",
      "serial": 215873
    },
    {
      "id": 377666,
      "datetime": "2026-07-06T12:18:09+00:00",
      "url": "https://t.me/pechalbeda200/377666",
      "dayKyiv": "2026-07-06",
      "serial": 215871
    },
    {
      "id": 377662,
      "datetime": "2026-07-06T11:58:27+00:00",
      "url": "https://t.me/pechalbeda200/377662",
      "dayKyiv": "2026-07-06",
      "serial": 215869
    },
    {
      "id": 377660,
      "datetime": "2026-07-06T11:09:50+00:00",
      "url": "https://t.me/pechalbeda200/377660",
      "dayKyiv": "2026-07-06",
      "serial": 215867
    },
    {
      "id": 377658,
      "datetime": "2026-07-06T11:03:37+00:00",
      "url": "https://t.me/pechalbeda200/377658",
      "dayKyiv": "2026-07-06",
      "serial": 215865
    },
    {
      "id": 377655,
      "datetime": "2026-07-06T10:58:05+00:00",
      "url": "https://t.me/pechalbeda200/377655",
      "dayKyiv": "2026-07-06",
      "serial": 215863
    },
    {
      "id": 377653,
      "datetime": "2026-07-06T10:49:52+00:00",
      "url": "https://t.me/pechalbeda200/377653",
      "dayKyiv": "2026-07-06",
      "serial": 215861
    },
    {
      "id": 377651,
      "datetime": "2026-07-06T10:47:49+00:00",
      "url": "https://t.me/pechalbeda200/377651",
      "dayKyiv": "2026-07-06",
      "serial": 215859
    },
    {
      "id": 377648,
      "datetime": "2026-07-06T10:44:32+00:00",
      "url": "https://t.me/pechalbeda200/377648",
      "dayKyiv": "2026-07-06",
      "serial": 215857
    },
    {
      "id": 377644,
      "datetime": "2026-07-06T10:42:00+00:00",
      "url": "https://t.me/pechalbeda200/377644",
      "dayKyiv": "2026-07-06",
      "serial": 215855
    },
    {
      "id": 377642,
      "datetime": "2026-07-06T10:39:49+00:00",
      "url": "https://t.me/pechalbeda200/377642",
      "dayKyiv": "2026-07-06",
      "serial": 215853
    }
  ]
}
