{
  "generatedAt": "2026-06-10T10:21:41.605Z",
  "channel": "pechalbeda200",
  "sourceUrl": "https://t.me/s/pechalbeda200",
  "methodology": {
    "windowDays": 30,
    "note": "Counts are based on public posts in Telegram web channel view. totalBySerial uses the numeric index at the start of entry text; fallback totalApproxByMaxPostId uses maximum observed channel post ID. This job should run often because the channel updates many times per day."
  },
  "counters": {
    "today": 33,
    "last7Days": 639,
    "last30Days": 686,
    "totalBySerial": 211811,
    "totalApproxByMaxPostId": 370050
  },
  "days": [
    {
      "day": "2026-06-03",
      "count": 119
    },
    {
      "day": "2026-06-04",
      "count": 100
    },
    {
      "day": "2026-06-05",
      "count": 111
    },
    {
      "day": "2026-06-06",
      "count": 66
    },
    {
      "day": "2026-06-07",
      "count": 72
    },
    {
      "day": "2026-06-08",
      "count": 81
    },
    {
      "day": "2026-06-09",
      "count": 104
    },
    {
      "day": "2026-06-10",
      "count": 33
    }
  ],
  "latestProofs": [
    {
      "id": 370050,
      "datetime": "2026-06-10T09:33:28+00:00",
      "url": "https://t.me/pechalbeda200/370050",
      "dayKyiv": "2026-06-10",
      "serial": 211811
    },
    {
      "id": 370047,
      "datetime": "2026-06-10T09:26:27+00:00",
      "url": "https://t.me/pechalbeda200/370047",
      "dayKyiv": "2026-06-10",
      "serial": 211809
    },
    {
      "id": 370044,
      "datetime": "2026-06-10T05:13:49+00:00",
      "url": "https://t.me/pechalbeda200/370044",
      "dayKyiv": "2026-06-10",
      "serial": 211807
    },
    {
      "id": 370042,
      "datetime": "2026-06-10T05:12:47+00:00",
      "url": "https://t.me/pechalbeda200/370042",
      "dayKyiv": "2026-06-10",
      "serial": 211805
    },
    {
      "id": 370040,
      "datetime": "2026-06-10T05:12:05+00:00",
      "url": "https://t.me/pechalbeda200/370040",
      "dayKyiv": "2026-06-10",
      "serial": 211803
    },
    {
      "id": 370034,
      "datetime": "2026-06-10T05:11:02+00:00",
      "url": "https://t.me/pechalbeda200/370034",
      "dayKyiv": "2026-06-10",
      "serial": 211801
    },
    {
      "id": 370031,
      "datetime": "2026-06-10T05:10:02+00:00",
      "url": "https://t.me/pechalbeda200/370031",
      "dayKyiv": "2026-06-10",
      "serial": 211798
    },
    {
      "id": 370029,
      "datetime": "2026-06-10T05:09:08+00:00",
      "url": "https://t.me/pechalbeda200/370029",
      "dayKyiv": "2026-06-10",
      "serial": 211796
    },
    {
      "id": 370027,
      "datetime": "2026-06-10T05:08:23+00:00",
      "url": "https://t.me/pechalbeda200/370027",
      "dayKyiv": "2026-06-10",
      "serial": 211794
    },
    {
      "id": 370025,
      "datetime": "2026-06-10T05:01:36+00:00",
      "url": "https://t.me/pechalbeda200/370025",
      "dayKyiv": "2026-06-10",
      "serial": 211792
    },
    {
      "id": 370023,
      "datetime": "2026-06-10T05:00:24+00:00",
      "url": "https://t.me/pechalbeda200/370023",
      "dayKyiv": "2026-06-10",
      "serial": 211790
    },
    {
      "id": 370021,
      "datetime": "2026-06-10T04:58:26+00:00",
      "url": "https://t.me/pechalbeda200/370021",
      "dayKyiv": "2026-06-10",
      "serial": 211788
    },
    {
      "id": 370018,
      "datetime": "2026-06-10T04:27:36+00:00",
      "url": "https://t.me/pechalbeda200/370018",
      "dayKyiv": "2026-06-10",
      "serial": 211786
    },
    {
      "id": 370014,
      "datetime": "2026-06-10T04:23:09+00:00",
      "url": "https://t.me/pechalbeda200/370014",
      "dayKyiv": "2026-06-10",
      "serial": 211784
    },
    {
      "id": 370008,
      "datetime": "2026-06-10T04:09:24+00:00",
      "url": "https://t.me/pechalbeda200/370008",
      "dayKyiv": "2026-06-10",
      "serial": 211781
    },
    {
      "id": 370005,
      "datetime": "2026-06-10T04:05:13+00:00",
      "url": "https://t.me/pechalbeda200/370005",
      "dayKyiv": "2026-06-10",
      "serial": 211779
    },
    {
      "id": 370003,
      "datetime": "2026-06-10T04:02:42+00:00",
      "url": "https://t.me/pechalbeda200/370003",
      "dayKyiv": "2026-06-10",
      "serial": 211777
    },
    {
      "id": 370000,
      "datetime": "2026-06-10T03:59:40+00:00",
      "url": "https://t.me/pechalbeda200/370000",
      "dayKyiv": "2026-06-10",
      "serial": 211775
    },
    {
      "id": 369998,
      "datetime": "2026-06-10T03:55:24+00:00",
      "url": "https://t.me/pechalbeda200/369998",
      "dayKyiv": "2026-06-10",
      "serial": 211773
    },
    {
      "id": 369996,
      "datetime": "2026-06-10T03:40:14+00:00",
      "url": "https://t.me/pechalbeda200/369996",
      "dayKyiv": "2026-06-10",
      "serial": 211771
    }
  ]
}
